ctools/__init__.py
ctools/application.py
ctools/aspect.py
ctools/authcode_validator.py
ctools/call.py
ctools/cdate.py
ctools/cdebug.py
ctools/cid.py
ctools/cjson.py
ctools/cron_lite.py
ctools/dict_wrapper.py
ctools/ex.py
ctools/metrics.py
ctools/patch.py
ctools/path_info.py
ctools/similar.py
ctools/sys_info.py
ctools/sys_log.py
ctools/ai/__init__.py
ctools/ai/llm_chat.py
ctools/ai/llm_client.py
ctools/ai/llm_exception.py
ctools/ai/mcp/__init__.py
ctools/ai/mcp/mcp_client.py
ctools/ai/tools/__init__.py
ctools/ai/tools/json_extract.py
ctools/ai/tools/quick_tools.py
ctools/ai/tools/think_process.py
ctools/ai/tools/tool_use_xml_parse.py
ctools/ai/tools/xml_extract.py
ctools/auto/__init__.py
ctools/auto/browser_element.py
ctools/auto/plan_area.py
ctools/auto/pty_process.py
ctools/auto/resource_bundle.py
ctools/auto/screenshot.py
ctools/auto/win_canvas.py
ctools/auto/win_control.py
ctools/cipher/__init__.py
ctools/cipher/aes_util.py
ctools/cipher/b64.py
ctools/cipher/czip.py
ctools/cipher/rsa.py
ctools/cipher/sign.py
ctools/cipher/sm_util.py
ctools/database/__init__.py
ctools/database/database.py
ctools/geo/__init__.py
ctools/geo/coord_trans.py
ctools/geo/douglas_rarefy.py
ctools/ml/image_process.py
ctools/ml/img_extractor.py
ctools/ml/ppi.py
ctools/office/__init__.py
ctools/office/cword.py
ctools/office/word_fill.py
ctools/office/word_fill_entity.py
ctools/pkg/__init__.py
ctools/pkg/dynamic_imp.py
ctools/pools/__init__.py
ctools/pools/process_pool.py
ctools/pools/thread_pool.py
ctools/stream/__init__.py
ctools/stream/ckafka.py
ctools/stream/credis.py
ctools/stream/mqtt_utils.py
ctools/util/__init__.py
ctools/util/cftp.py
ctools/util/cklock.py
ctools/util/compile_util.py
ctools/util/config_util.py
ctools/util/env_config.py
ctools/util/html_soup.py
ctools/util/http_util.py
ctools/util/image_process.py
ctools/util/jb_cut.py
ctools/util/snow_id.py
ctools/web/__init__.py
ctools/web/aio_web_server.py
ctools/web/api_result.py
ctools/web/bottle_web_base.py
gomyck_tools-1.5.6.dist-info/licenses/LICENSE
gomyck_tools-1.5.6.dist-info/METADATA
gomyck_tools-1.5.6.dist-info/WHEEL
gomyck_tools-1.5.6.dist-info/top_level.txt
gomyck_tools-1.5.6.dist-info/RECORD
