Metadata-Version: 2.4
Name: gomyck-tools
Version: 1.5.6
Summary: A tools collection for python development by hao474798383
Author-email: gomyck <hao474798383@163.com>
License-Expression: Apache-2.0
Requires-Python: >=3.11
License-File: LICENSE
Requires-Dist: jsonpickle~=4.1.1
Requires-Dist: SQLAlchemy~=2.0.44
Requires-Dist: chardet~=5.2.0
Requires-Dist: psycopg2-binary~=2.9.11
Requires-Dist: croniter~=5.0.1
Requires-Dist: gmssl~=3.2.2
Requires-Dist: psutil~=6.1.0
Requires-Dist: jsonpath_ng~=1.7.0
Requires-Dist: bottle~=0.13.4
Requires-Dist: requests~=2.32.3
Requires-Dist: urllib3~=1.26.20
Requires-Dist: kafka-python~=2.3.0
Requires-Dist: bs4~=0.0.2
Requires-Dist: paho-mqtt~=2.1.0
Requires-Dist: fuzzywuzzy~=0.18.0
Requires-Dist: pymysql~=1.1.1
Requires-Dist: pyzipper==0.3.6
Requires-Dist: prometheus_client==0.23.1
Requires-Dist: paramiko==3.5.0
Requires-Dist: pyjwt==2.10.1
Requires-Dist: cryptography==46.0.3
Requires-Dist: redis==7.1.0
Requires-Dist: uvloop>=0.22.1
Requires-Dist: pyyaml>=6.0.3
Requires-Dist: uiautomation>=2.0.20
Provides-Extra: kwc
Requires-Dist: imageio>=2.37.0; extra == "kwc"
Requires-Dist: wordcloud>=1.9.4; extra == "kwc"
Requires-Dist: jieba==0.42.1; extra == "kwc"
Requires-Dist: paddlepaddle==3.2.2; extra == "kwc"
Provides-Extra: cut
Requires-Dist: jieba==0.42.1; extra == "cut"
Requires-Dist: paddlepaddle==3.2.2; extra == "cut"
Provides-Extra: ml
Requires-Dist: scikit-learn>=1.7.1; extra == "ml"
Requires-Dist: pandas>=2.3.2; extra == "ml"
Requires-Dist: lxml>=6.0.1; extra == "ml"
Requires-Dist: xlrd>=2.0.2; extra == "ml"
Provides-Extra: xj-plate-server
Requires-Dist: paddlepaddle==3.2.2; extra == "xj-plate-server"
Dynamic: license-file
